{
    "id": 11330,
    "name": "Le Prix à payer",
    "release_date": "1997-06-25",
    "runtime_in_minutes": 117,
    "genres": [
        "Action",
        "Drame",
        "Policier"
    ],
    "synopsis": "\n                    Quatre amies noires vivent dans un quartier pauvre de Los Angeles. Leur sort quotidien est la misère et le racisme, qui les lient plus que jamais. Lorsque le frère de l'une d'entre elles est tué lors d'une bavure policière, leur destin bascule. Elles choisissent la marginalité et les braquages de banques, récoltant plus d'argent en quelques semaines qu'en des années de labeur assidu. Mais la médaille a un revers des plus douloureux.\n        \n            ",
    "reviews": [
        {
            "id": "review_40644004",
            "author": "\n                            Mathieu Dumont-Roty\n            \n                    ",
            "date": "2014-01-16",
            "rating": 3.0,
            "text_content": "\n                    Un bon film féministe qui aurait pu être encore meilleur si il n'utilisait pas autant la surenchère. 13/20\n        \n            ",
            "likes": 2,
            "dislikes": 1
        },
        {
            "id": "review_28596433",
            "author": "\n                            asmenez\n            \n                    ",
            "date": "2012-02-3",
            "rating": 5.0,
            "text_content": "\n                    classic pour moi franchement il est pas très connu dommage tanpis pour eux\n        \n            ",
            "likes": 2,
            "dislikes": 3
        },
        {
            "id": "review_36514486",
            "author": "\n                            bsalvert\n            \n                            \n                    ",
            "date": "2013-03-22",
            "rating": 2.0,
            "text_content": "\n                    Un film qui pourrait être sympa s'il ne tirait pas vers la morale.",
            "likes": 2,
            "dislikes": 4
        },
        {
            "id": "review_18851240",
            "author": "\n                            hyrule\n            \n                    ",
            "date": "2011-07-27",
            "rating": 2.0,
            "text_content": "\n                    Scénario déjà-vu, actrices réellement en dessous de tout, on ne peut pas dire que ce film soit une réussite... On dirait un clip de R'N'B mais très très long (déjà qu'à l'origine, c'est long...). Bref, très stéréotypé, des filles qui se croient le centre du monde simplement parce qu'elles vivent dans la misère... Une série B à éviter en fait.\n        \n            ",
            "likes": 1,
            "dislikes": 1
        },
        {
            "id": "review_16060606",
            "author": "\n                            chrischambers86\n            \n                    ",
            "date": "2010-07-26",
            "rating": 1.0,
            "text_content": "\n                    Une pour toutes...et une pour toutes! Quatre jeunes femmes noires dècident de prendre leur destin en main et de sortir de la misère...le flingue à la main! Menèe faussement par la chanteuse Queen Latifah, Jada Pinkett, Blair Underwood et Vivica A.Fox, cette histoire violente - entre polar et chronique sociale - ,qui prend des allures de clip vidèo, brosse un tableau sans concession d'une Amèrique où la misère et les injustices poussent un groupe de braves filles au dèsespoir (les pauvres à croire qu'elles sont les seules au monde à être au bord du gouffre) puis à la dèlinquance dans un quartier chaud de Los Angeles pour un thriller qui sonne faux du dèbut à la fin! A èviter sauf si vous vous apprêtez à commettre un casse...\n        \n            ",
            "likes": 1,
            "dislikes": 1
        },
        {
            "id": "review_22857048",
            "author": "\n                            Machriasi\n            \n                    ",
            "date": "2011-07-19",
            "rating": 3.5,
            "text_content": "\n                    Souvent absurde et prévisible, les actrices jouent mal elles sont super mal habillées (en espérant que ce n'est pas représentatif de l'époque) bref beaucoup de stéréotypes  mais j'ai quand même beaucoup aimé grâce au thème, au casting et je me suis bien tapée des barres grâce a la fin plus que grotesque",
            "likes": 1,
            "dislikes": 1
        },
        {
            "id": "review_40903484",
            "author": "\n                             Un visiteur \n            \n                    ",
            "date": "2014-02-6",
            "rating": 3.5,
            "text_content": "\n                    Il m'avait marqué ce film, dans la série des films de braqueurs ou braqueuses on retiendra celui là, du haut niveau, une bonne histoire, des personnages attachants malgré leurs déboires et l'escalade dans la violence.",
            "likes": 1,
            "dislikes": 1
        },
        {
            "id": "review_33838494",
            "author": "\n                             Un visiteur \n            \n                    ",
            "date": "2012-10-4",
            "rating": 5.0,
            "text_content": "\n                    je l'ai vu quand j'avais 13 , 14 ans, il m'a bcp  marqué par son tout!",
            "likes": 0,
            "dislikes": 1
        },
        {
            "id": "review_1028351289",
            "author": "\n                            Alain D.\n            \n                            \n                    ",
            "date": "2023-12-15",
            "rating": 3.5,
            "text_content": "\n                    Un film dur et plein d'action réalisé par F. Gary Gray. Avec \" Le Prix à payer\" il nous propose un polar sanglant, dénonçant les bavures policières, le machisme des employeurs, le sexisme et le racisme présent à Los Angeles dans les années 70 ;  problèmes qui hélas n'ont pas disparus depuis. ",
            "likes": 1,
            "dislikes": 0
        },
        {
            "id": "review_1002373035",
            "author": "\n                            jthuil\n            \n                    ",
            "date": "2020-02-9",
            "rating": 4.5,
            "text_content": "\n                    Dans un premier temps, la société semble un peu clivée dans ce film à mi-chemin entre le polar et la chronique sociale. D'un côté, les policiers incompétents ou sadiques, et de l'autre, les gentils afro-américians qui souffrent de toutes les oppressions, enclavés dans le ghetto. On croirait même presque assister à une apologie de la délinquance ou à sa justification. Heureusement, des nuances apparaissent progressivement et la vapeur s'inverse. Et surtout, on se retrouve bien obligé de saluer la générosité des quatre formidables actrices qui portent le film à bout de bras et assènent douloureusement la morale de cette histoire, dont le final a littéralement bouleversé bon nombre de spectateurs. In-extremis, on peut donc parler d'une belle réussite.\n        \n            ",
            "likes": 1,
            "dislikes": 0
        },
        {
            "id": "review_15536123",
            "author": "\n                             Un visiteur \n            \n                    ",
            "date": "2009-09-16",
            "rating": 1.0,
            "text_content": "\n                    Digne d'une série B, scénario américain pour nanard\n        \n            ",
            "likes": 0,
            "dislikes": 1
        },
        {
            "id": "review_1008174124",
            "author": "\n                            Xavière \n            \n                    ",
            "date": "2020-06-21",
            "rating": 5.0,
            "text_content": "\n                    Film génial ... Un chef d'œuvre... C'est un film émouvant qui touche des sujets tabous et sensibles. La B.O aussi est géniale... Je recommande ce film qui m'émeut à chaque fois et qui est incroyablement bien interprété.\n        \n            ",
            "likes": 1,
            "dislikes": 0
        },
        {
            "id": "review_1013774263",
            "author": "\n                            Floki\n            \n                    ",
            "date": "2021-03-15",
            "rating": 4.0,
            "text_content": "\n                    Un film que j'ai vu, il y a maintenant très longtemps, j'étais jeune, mais il m'avait marqué, ça a longtemps était l'un de mes films favoris. L'histoire est magnifique et très réaliste malheureusement. Il a un peu mal vieilli quand on le revoit maintenant, mais ça reste tout de même un TRÈS bon film.\n        \n            ",
            "likes": 1,
            "dislikes": 0
        },
        {
            "id": "review_58255327",
            "author": "\n                            Gildas Benefice\n            \n                    ",
            "date": "2018-02-3",
            "rating": 5.0,
            "text_content": "\n                    Chef d’œuvre, pour pas oser dire mon meilleur de touts les temps. Être acteur est un  métier et les actrices de ce filme le prouve avec leur jeu, on s'y croirait dans la vraie vie. A regarder encore et encore sans modération. F. Gary Grey réalisateur fantastique\n        \n            ",
            "likes": 0,
            "dislikes": 2
        },
        {
            "id": "review_77030",
            "author": "\n                             Un visiteur \n            \n                    ",
            "date": "2006-09-29",
            "rating": 5.0,
            "text_content": "\n                    4 Femmes noires qui veulent s'en sortir en sont réduites à commettre des cambriolages.Une bande originale parfaite (en particulier MISSIN YOU interprétée par Brandy,Tamia et Chaka Khan).",
            "likes": 0,
            "dislikes": 0
        },
        {
            "id": "review_6685050",
            "author": "\n                             Un visiteur \n            \n                    ",
            "date": "2008-02-19",
            "rating": 5.0,
            "text_content": "\n                    Un film magnifique et je pense qu'il devrait être beaucoup plus connu... Un très bon scénario, de bon acteurs, avec une histoire dramatique et émouvante. A VOIR !!!\n        \n            ",
            "likes": 0,
            "dislikes": 0
        },
        {
            "id": "review_5509374",
            "author": "\n                             Un visiteur \n            \n                    ",
            "date": "2007-12-16",
            "rating": 5.0,
            "text_content": "\n                    Un oeuvre exceptionnellement intense et dramatique.",
            "likes": 0,
            "dislikes": 0
        },
        {
            "id": "review_20923930",
            "author": "\n                             Un visiteur \n            \n                    ",
            "date": "2010-09-1",
            "rating": 5.0,
            "text_content": "\n                    tres bon film d action et d emotion un bon moment de cinéma vraiment dommage ke le dvd n existe pas\n        \n            ",
            "likes": 0,
            "dislikes": 1
        },
        {
            "id": "review_16198615",
            "author": "\n                             Un visiteur \n            \n                    ",
            "date": "2009-12-12",
            "rating": 0.5,
            "text_content": "\n                    un tres beau film\n        \n            ",
            "likes": 0,
            "dislikes": 1
        },
        {
            "id": "review_9425708",
            "author": "\n                             Un visiteur \n            \n                    ",
            "date": "2008-07-25",
            "rating": 4.0,
            "text_content": "\n                    Pas mal du tout. Le film est poignant par moment car il montre bien la détresse de ces femmes qui souhaitent a tout prix, justement, quitter leur ghetto natal. Les actrice sont toutes excellentes, avec une mention spéciale à Queen Latifah et à Jada Pinket Smith.\n        \n            ",
            "likes": 0,
            "dislikes": 0
        },
        {
            "id": "review_60099712",
            "author": "\n                             Un visiteur \n            \n                    ",
            "date": "2018-08-21",
            "rating": 5.0,
            "text_content": "\n                    Très beau film. Des actrices merveilleuses chacune avec leur tempérament en plus  4 black women... film dramatique, comme son titre français, qui m'a fait énormément pleurer.... à voir revoir\n        \n            ",
            "likes": 0,
            "dislikes": 0
        },
        {
            "id": "review_24778201",
            "author": "\n                             Un visiteur \n            \n                    ",
            "date": "2011-05-7",
            "rating": 5.0,
            "text_content": "\n                    Excellent film ! Terrible histoire ! Et dans tout les sens du terme :/\n        \n            ",
            "likes": 0,
            "dislikes": 2
        },
        {
            "id": "review_1022153876",
            "author": "\n                             Un visiteur \n            \n                    ",
            "date": "2022-10-20",
            "rating": 4.5,
            "text_content": "\n                    Sérieusement sous-estimé. La fin est juste poignante. Latifah Queen joue très bien son rôle. J'aime beaucoup l'idée que ce soit toutes des femmes\n        \n            ",
            "likes": 0,
            "dislikes": 0
        },
        {
            "id": "review_6455840",
            "author": "\n                             Un visiteur \n            \n                    ",
            "date": "2008-02-8",
            "rating": 5.0,
            "text_content": "\n                    .\n        \n            ",
            "likes": 0,
            "dislikes": 0
        }
    ]
}